llama_index/embeddings/cohere/__init__.py
llama_index/embeddings/cohere/base.py
llama_index_embeddings_cohere-0.6.0.dist-info/METADATA
llama_index_embeddings_cohere-0.6.0.dist-info/WHEEL
llama_index_embeddings_cohere-0.6.0.dist-info/licenses/LICENSE
llama_index_embeddings_cohere-0.6.0.dist-info/RECORD
