Metadata-Version: 2.4
Name: llama-index-embeddings-cohere
Version: 0.6.0
Summary: llama-index embeddings cohere integration
Author-email: Your Name <you@example.com>
License-Expression: MIT
License-File: LICENSE
Requires-Python: <4.0,>=3.9
Requires-Dist: cohere<6,>=5.15
Requires-Dist: llama-index-core<0.14,>=0.13.0
